lcpfn/__init__.py
lcpfn/bar_distribution.py
lcpfn/curves.py
lcpfn/decoders.py
lcpfn/domhan_prior.py
lcpfn/encoders.py
lcpfn/initializers.py
lcpfn/layer.py
lcpfn/model.py
lcpfn/positional_encodings.py
lcpfn/train.py
lcpfn/train_lcpfn.py
lcpfn/transformer.py
lcpfn/utils.py
lcpfn/version.py
lcpfn/priors/__init__.py
lcpfn/priors/prior.py
lcpfn/priors/utils.py
lcpfn-0.1.3.dist-info/LICENSE
lcpfn-0.1.3.dist-info/METADATA
lcpfn-0.1.3.dist-info/WHEEL
lcpfn-0.1.3.dist-info/top_level.txt
lcpfn-0.1.3.dist-info/RECORD
