Metadata-Version: 2.1
Name: lcpfn
Version: 0.1.3
Summary: In-context Bayesian Learning Curve Extrapolation
Author-email: Steven Adriaensen <adriaens@cs.uni-freiburg.de>, Herilalaina Rakotoarison <rakotoah@cs.uni-freiburg.de>, Samuel Müller <muellesa@cs.uni-freiburg.de>, Frank Hutter <fh@cs.uni-freiburg.de>
License: MIT License
Project-URL: homepage, https://github.com/automl/lcpfn
Project-URL: repository, https://github.com/automl/lcpfn
Project-URL: bugtracker, https://github.com/automl/lcpfn/issues
Classifier: Intended Audience :: Science/Research
Classifier: License :: OSI Approved :: MIT License
Classifier: Programming Language :: Python
Classifier: Topic :: Software Development
Classifier: Topic :: Scientific/Engineering
Classifier: Operating System :: Unix
Classifier: Operating System :: MacOS
Classifier: Programming Language :: Python :: 3
Classifier: Programming Language :: Python :: 3.9
Classifier: Programming Language :: Python :: 3.10
Classifier: Programming Language :: Python :: 3.11
Requires-Python: <3.12,>=3.9
License-File: LICENSE
Requires-Dist: torch <=1.11.0
Requires-Dist: numpy <2,>=1.21.2
Requires-Dist: requests >=2.23.0
